scfocus/Analysis.py
scfocus/__init__.py
scfocus/cli.py
scfocus/environment.py
scfocus/focus.py
scfocus/model.py
scfocus/utils.py
scfocus-0.0.5.dist-info/LICENSE
scfocus-0.0.5.dist-info/METADATA
scfocus-0.0.5.dist-info/WHEEL
scfocus-0.0.5.dist-info/entry_points.txt
scfocus-0.0.5.dist-info/top_level.txt
scfocus-0.0.5.dist-info/RECORD
