Metadata-Version: 2.1
Name: scfocus
Version: 0.0.5
Summary: single cell reinforcement learning for focusing
Home-page: https://github.com/PeterPonyu/scfocus
Author: Zeyu Fu
Author-email: fuzeyu99@126.com
License: MIT
Classifier: License :: OSI Approved :: MIT License
Classifier: Development Status :: 4 - Beta
Classifier: Programming Language :: Python :: 3
Classifier: Intended Audience :: Science/Research
Classifier: Topic :: Scientific/Engineering :: Bio-Informatics
Requires-Python: >=3.9
License-File: LICENSE
Requires-Dist: scanpy>=1.10.4
Requires-Dist: torch>=1.13.1
Requires-Dist: joblib>=1.2.0
Requires-Dist: tqdm>=4.64.1
Requires-Dist: streamlit>=1.24.0
